enhancements/__init__.py
enhancements/__version__.py
enhancements/cli.py
enhancements/config.py
enhancements/contextmanager.py
enhancements/examples.py
enhancements/exceptions.py
enhancements/modules.py
enhancements/plugins.py
enhancements/process.py
enhancements/py.typed
enhancements/returncode.py
enhancements-0.4.0.dist-info/LICENSE
enhancements-0.4.0.dist-info/METADATA
enhancements-0.4.0.dist-info/WHEEL
enhancements-0.4.0.dist-info/top_level.txt
enhancements-0.4.0.dist-info/RECORD
