Metadata-Version: 2.1
Name: enhancements
Version: 0.4.0
Summary: Plugin System for SSH-MITM server
Home-page: https://enhancements.readthedocs.io/
Author: Manfred Kaiser
Author-email: manfred.kaiser@ssh-mitm.at
License: UNKNOWN
Project-URL: Source, https://github.com/ssh-mitm/python-enhancements
Project-URL: Tracker, https://github.com/ssh-mitm/python-enhancements/issues
Keywords: development configparser argparse
Platform: UNKNOWN
Classifier: Programming Language :: Python :: 3
Classifier: Programming Language :: Python :: 3.6
Classifier: Programming Language :: Python :: 3.7
Classifier: Programming Language :: Python :: 3.8
Classifier: Programming Language :: Python :: 3.9
Classifier: Programming Language :: Python :: 3.10
Classifier: License :: OSI Approved :: GNU Lesser General Public License v3 (LGPLv3)
Classifier: Development Status :: 5 - Production/Stable
Requires-Python: >= 3.6
License-File: LICENSE
Requires-Dist: argcomplete
Requires-Dist: typeguard
